[
  {
    "plane_id": "166",
    "battery_id": 1,
    "compare_backend_enabled": true,
    "n_events_compared": 553,
    "median_abs_backend_delta_pct": 2.842170943040401e-14,
    "p95_abs_backend_delta_pct": 2.984279490192421e-13,
    "max_abs_backend_delta_pct": 3.410605131648481e-13
  },
  {
    "plane_id": "166",
    "battery_id": 2,
    "compare_backend_enabled": true,
    "n_events_compared": 553,
    "median_abs_backend_delta_pct": 1.4210854715202004e-14,
    "p95_abs_backend_delta_pct": 2.1316282072803006e-13,
    "max_abs_backend_delta_pct": 2.7000623958883807e-13
  }
]