{
  "plane_id": "166",
  "rt_profile": "current",
  "battery_ids_processed": [
    1,
    2
  ],
  "n_events_total": 1106,
  "n_events_per_battery": {
    "1": 553,
    "2": 553
  },
  "n_events_dropped_missing_observed_soh": 0,
  "sigma_base_pct_per_battery": {
    "1": 0.75,
    "2": 0.75
  },
  "q_day_sigma_pct": 0.08,
  "raw_total_variation_per_battery": {
    "1": 484.0,
    "2": 469.0
  },
  "smoothed_total_variation_per_battery": {
    "1": 41.47572513360557,
    "2": 39.80418429993698
  },
  "raw_max_upward_jump_pct_per_battery": {
    "1": 29.0,
    "2": 25.0
  },
  "smoothed_max_upward_jump_pct_per_battery": {
    "1": 0.3770357745290198,
    "2": 0.40662262767720847
  },
  "fraction_events_with_condition_multiplier_gt_3": {
    "1": 0.9493670886075949,
    "2": 0.9475587703435805
  },
  "notes": "FilterPy latent SOH is the canonical output."
}